Workbook

Sheet Sheet1
A1: Order_Id | B1: Date | C1: Product | D1: Pieces | E1: Price | F1: Payment_Method | G1: Manager | H1: City | I1: Revenu
A2: A001 | B2: 46296 | C2: Solar pad | D2: 1 | E2: 55000 | F2: Cash | G2: Arun kumar | H2: Chennai | I2: =Table1[[#This Row],[Pieces]]*Table1[[#This Row],[Price]] -> 55000
A3: A002 | B3: 46297 | C3: PowerBatter | D3: 1 | E3: 49000 | F3: Gpay | G3: Ragul | H3: Pondy | I3: =Table1[[#This Row],[Pieces]]*Table1[[#This Row],[Price]] -> 49000
A4: A003 | B4: 46298 | C4: Books | D4: 10 | E4: 2500 | F4: Cash | G4: Priya | H4: Pondy | I4: =Table1[[#This Row],[Pieces]]*Table1[[#This Row],[Price]] -> 25000
A5: A004 | B5: 46299 | C5: Notes | D5: 40 | E5: 5000 | F5: Gpay | G5: Hema | H5: Chennai | I5: =Table1[[#This Row],[Pieces]]*Table1[[#This Row],[Price]] -> 200000
A6: A005 | B6: 46300 | C6: Laptop | D6: 2 | E6: 140000 | F6: Cash | G6: Deepa | H6: Chennai | I6: =Table1[[#This Row],[Pieces]]*Table1[[#This Row],[Price]] -> 280000
A7: A006 | B7: 46301 | C7: Phone | D7: 1 | E7: 25000 | F7: Gpay | G7: Arun | H7: Trichy | I7: =Table1[[#This Row],[Pieces]]*Table1[[#This Row],[Price]] -> 25000
A8: A007 | B8: 46302 | C8: Tab | D8: 1 | E8: 15000 | F8: Cash | G8: Divya | H8: Selam | I8: =Table1[[#This Row],[Pieces]]*Table1[[#This Row],[Price]] -> 15000
A9: A008 | B9: 46303 | C9: Tv | D9: 1 | E9: 101500 | F9: Cash | G9: Ragul | H9: Pondy | I9: =Table1[[#This Row],[Pieces]]*Table1[[#This Row],[Price]] -> 101500
A10: A009 | B10: 46304 | C10: Watch | D10: 2 | E10: 6000 | F10: Gpay | G10: Arun kumar | H10: Chennai | I10: =Table1[[#This Row],[Pieces]]*Table1[[#This Row],[Price]] -> 12000
A11: A010 | B11: 46305 | C11: Board | D11: 1 | E11: 2500 | F11: Cash | G11: Priya | H11: Pondy | I11: =Table1[[#This Row],[Pieces]]*Table1[[#This Row],[Price]] -> 2500
A12: A011 | B12: 46306 | C12: Speaker | D12: 1 | E12: 80000 | F12: Gpay | G12: Hema | H12: Trichy | I12: =Table1[[#This Row],[Pieces]]*Table1[[#This Row],[Price]] -> 80000
A13: A012 | B13: 46307 | C13: Snacks | D13: 1 | E13: 1000 | F13: Cash | G13: Deepa | H13: Chennai | I13: =Table1[[#This Row],[Pieces]]*Table1[[#This Row],[Price]] -> 1000
A14: A013 | B14: 46308 | C14: Tablets | D14: 10 | E14: 25000 | F14: Gpay | G14: Arun | H14: Selam | I14: =Table1[[#This Row],[Pieces]]*Table1[[#This Row],[Price]] -> 250000 | M14: Column1
A15: A014 | B15: 46309 | C15: ToyCycle | D15: 1 | E15: 14000 | F15: Gpay | G15: Priya | H15: Pondy | I15: =Table1[[#This Row],[Pieces]]*Table1[[#This Row],[Price]] -> 14000
A16: A015 | B16: 46310 | C16: Pen | D16: 30 | E16: 800 | F16: Cash | G16: Ragul | H16: Pondy | I16: =Table1[[#This Row],[Pieces]]*Table1[[#This Row],[Price]] -> 24000 | M16: Mean | N16: 121548.39
A17: A016 | B17: 46311 | C17: Solar pad | D17: 1 | E17: 55000 | F17: Cash | G17: Arun kumar | H17: Chennai | I17: =Table1[[#This Row],[Pieces]]*Table1[[#This Row],[Price]] -> 55000 | M17: Standard Error | N17: 48668.935
A18: A017 | B18: 46312 | C18: PowerBatter | D18: 1 | E18: 49000 | F18: Cash | G18: Ragul | H18: Pondy | I18: =Table1[[#This Row],[Pieces]]*Table1[[#This Row],[Price]] -> 49000 | M18: Median | N18: 25000
A19: A018 | B19: 46313 | C19: Books | D19: 10 | E19: 2500 | F19: Cash | G19: Priya | H19: Pondy | I19: =Table1[[#This Row],[Pieces]]*Table1[[#This Row],[Price]] -> 25000 | M19: Mode | N19: 25000
A20: A019 | B20: 46314 | C20: Notes | D20: 40 | E20: 5000 | F20: Cash | G20: Hema | H20: Chennai | I20: =Table1[[#This Row],[Pieces]]*Table1[[#This Row],[Price]] -> 200000 | M20: Standard Deviation | N20: 270977.16
A21: A020 | B21: 46315 | C21: Laptop | D21: 2 | E21: 140000 | F21: Cash | G21: Deepa | H21: Chennai | I21: =Table1[[#This Row],[Pieces]]*Table1[[#This Row],[Price]] -> 280000 | M21: Sample Variance | N21: 7.3428623e+10
A22: A021 | B22: 46316 | C22: Phone | D22: 1 | E22: 25000 | F22: Cash | G22: Arun | H22: Trichy | I22: =Table1[[#This Row],[Pieces]]*Table1[[#This Row],[Price]] -> 25000 | M22: Kurtosis | N22: 23.975238
A23: A022 | B23: 46317 | C23: Tab | D23: 1 | E23: 15000 | F23: Cash | G23: Divya | H23: Selam | I23: =Table1[[#This Row],[Pieces]]*Table1[[#This Row],[Price]] -> 15000 | M23: Skewness | N23: 4.6757729
A24: A023 | B24: 46318 | C24: Tv | D24: 1 | E24: 101500 | F24: Cash | G24: Ragul | H24: Pondy | I24: =Table1[[#This Row],[Pieces]]*Table1[[#This Row],[Price]] -> 101500 | M24: Range | N24: 1499000
A25: A024 | B25: 46319 | C25: Watch | D25: 2 | E25: 6000 | F25: Cash | G25: Arun kumar | H25: Chennai | I25: =Table1[[#This Row],[Pieces]]*Table1[[#This Row],[Price]] -> 12000 | M25: Minimum | N25: 1000
A26: A025 | B26: 46320 | C26: Board | D26: 1 | E26: 2500 | F26: Cash | G26: Priya | H26: Pondy | I26: =Table1[[#This Row],[Pieces]]*Table1[[#This Row],[Price]] -> 2500 | M26: Maximum | N26: 1500000
A27: A026 | B27: 46321 | C27: Speaker | D27: 1 | E27: 80000 | F27: Cash | G27: Hema | H27: Trichy | I27: =Table1[[#This Row],[Pieces]]*Table1[[#This Row],[Price]] -> 80000 | M27: Sum | N27: 3768000
A28: A027 | B28: 46322 | C28: Snacks | D28: 1 | E28: 1000 | F28: Cash | G28: Deepa | H28: Chennai | I28: =Table1[[#This Row],[Pieces]]*Table1[[#This Row],[Price]] -> 1000 | M28: Count | N28: 31
A29: A028 | B29: 46323 | C29: Tablets | D29: 10 | E29: 25000 | F29: Cash | G29: Arun | H29: Selam | I29: =Table1[[#This Row],[Pieces]]*Table1[[#This Row],[Price]] -> 250000
A30: A029 | B30: 46324 | C30: ToyCycle | D30: 1 | E30: 14000 | F30: Cash | G30: Priya | H30: Pondy | I30: =Table1[[#This Row],[Pieces]]*Table1[[#This Row],[Price]] -> 14000
A31: A030 | B31: 46325 | C31: Pen | D31: 30 | E31: 800 | F31: Cash | G31: Ragul | H31: Pondy | I31: =Table1[[#This Row],[Pieces]]*Table1[[#This Row],[Price]] -> 24000
A32: A031 | B32: 46326 | C32: White Cover | D32: 300 | E32: 5000 | F32: Gpay | G32: vivek | H32: Selam | I32: =Table1[[#This Row],[Pieces]]*Table1[[#This Row],[Price]] -> 1500000

Sheet Sheet2
A1: Best selling Product | B1: Laptop
A2: Revenu Breakdown Over Time | O2: Date | P2: Sum of Revenu
A3: Revenu Breakdown By City | D3: Date | E3: Sum of Revenu | O3: 46296 | P3: 55000
D4: 46326 | E4: 1500000 | O4: 46297 | P4: 49000
D5: 46325 | E5: 24000 | O5: 46298 | P5: 25000
D6: 46324 | E6: 14000 | O6: 46299 | P6: 200000
D7: 46323 | E7: 250000 | O7: 46300 | P7: 280000
D8: 46322 | E8: 1000 | O8: 46301 | P8: 25000
D9: 46321 | E9: 80000 | O9: 46302 | P9: 15000
D10: 46320 | E10: 2500 | O10: 46303 | P10: 101500
D11: 46319 | E11: 12000 | O11: 46304 | P11: 12000
D12: 46318 | E12: 101500 | O12: 46305 | P12: 2500
D13: 46317 | E13: 15000 | O13: 46306 | P13: 80000
D14: 46316 | E14: 25000 | O14: 46307 | P14: 1000
D15: 46315 | E15: 280000 | O15: 46308 | P15: 250000
... D33: 46297 | E33: 49000 | O33: 46326 | P33: 1500000
D34: 46296 | E34: 55000

Sheet Sheet3
B3: Select Manager | C3: Deepa | N3: Arun kumar
N4: Ragul
B5: Solar pad | C5: =SUMIFS(Table1[Revenu],Table1[Manager],Sheet3!$C$3,Table1[Product],Sheet3!$B5) -> 0 | N5: Priya
B6: PowerBatter | C6: =SUMIFS(Table1[Revenu],Table1[Manager],Sheet3!$C$3,Table1[Product],Sheet3!$B6) -> 0 | N6: Hema
B7: Books | C7: =SUMIFS(Table1[Revenu],Table1[Manager],Sheet3!$C$3,Table1[Product],Sheet3!$B7) -> 0 | N7: Deepa
B8: Notes | C8: =SUMIFS(Table1[Revenu],Table1[Manager],Sheet3!$C$3,Table1[Product],Sheet3!$B8) -> 0 | N8: Arun
B9: Laptop | C9: =SUMIFS(Table1[Revenu],Table1[Manager],Sheet3!$C$3,Table1[Product],Sheet3!$B9) -> 560000 | N9: Divya
B10: Phone | C10: =SUMIFS(Table1[Revenu],Table1[Manager],Sheet3!$C$3,Table1[Product],Sheet3!$B10) -> 0 | N10: Ragul
B11: Tab | C11: =SUMIFS(Table1[Revenu],Table1[Manager],Sheet3!$C$3,Table1[Product],Sheet3!$B11) -> 0 | N11: Arun kumar
B12: Tv | C12: =SUMIFS(Table1[Revenu],Table1[Manager],Sheet3!$C$3,Table1[Product],Sheet3!$B12) -> 0 | N12: Priya
B13: Watch | C13: =SUMIFS(Table1[Revenu],Table1[Manager],Sheet3!$C$3,Table1[Product],Sheet3!$B13) -> 0 | N13: Hema
B14: Board | C14: =SUMIFS(Table1[Revenu],Table1[Manager],Sheet3!$C$3,Table1[Product],Sheet3!$B14) -> 0 | N14: Deepa
B15: Speaker | C15: =SUMIFS(Table1[Revenu],Table1[Manager],Sheet3!$C$3,Table1[Product],Sheet3!$B15) -> 0 | N15: Arun
B16: Snacks | C16: =SUMIFS(Table1[Revenu],Table1[Manager],Sheet3!$C$3,Table1[Product],Sheet3!$B16) -> 2000 | N16: Priya
B17: Tablets | C17: =SUMIFS(Table1[Revenu],Table1[Manager],Sheet3!$C$3,Table1[Product],Sheet3!$B17) -> 0 | N17: Ragul
B18: ToyCycle | C18: =SUMIFS(Table1[Revenu],Table1[Manager],Sheet3!$C$3,Table1[Product],Sheet3!$B18) -> 0
B19: Pen | C19: =SUMIFS(Table1[Revenu],Table1[Manager],Sheet3!$C$3,Table1[Product],Sheet3!$B19) -> 0
B20: Total | C20: =SUM(C9) -> 560000
